tibetan_sanskrit_transliteration_data/__init__.py
tibetan_sanskrit_transliteration_data/replacements.csv
tibetan_sanskrit_transliteration_data-0.1.3.dist-info/METADATA
tibetan_sanskrit_transliteration_data-0.1.3.dist-info/WHEEL
tibetan_sanskrit_transliteration_data-0.1.3.dist-info/top_level.txt
tibetan_sanskrit_transliteration_data-0.1.3.dist-info/RECORD
