Metadata-Version: 2.4
Name: tibetan-sanskrit-transliteration-data
Version: 0.1.3
Summary: Shared replacement map data for transliterating Tibetan-encoded Sanskrit mantras
Author: Padmakara
License: MIT
Project-URL: Homepage, https://github.com/jerefrer/tibetan-sanskrit-transliteration-data
Project-URL: Repository, https://github.com/jerefrer/tibetan-sanskrit-transliteration-data
Keywords: tibetan,sanskrit,transliteration,iast,phonetics,mantra,data
Classifier: Development Status :: 5 - Production/Stable
Classifier: Intended Audience :: Developers
Classifier: License :: OSI Approved :: MIT License
Classifier: Programming Language :: Python :: 3
Classifier: Programming Language :: Python :: 3.8
Classifier: Programming Language :: Python :: 3.9
Classifier: Programming Language :: Python :: 3.10
Classifier: Programming Language :: Python :: 3.11
Classifier: Programming Language :: Python :: 3.12
Requires-Python: >=3.8
